{
  "settings": {
    "migrated": 2,
    "iconPacksPath": ".obsidian/plugins/obsidian-icon-folder/icons",
    "fontSize": 16,
    "emojiStyle": "native",
    "iconColor": null,
    "recentlyUsedIcons": [
      "IbPlay",
      "RiSettings3Line",
      "LiCoffee",
      "RiUserSettingsLine",
      "SiCplusplus"
    ],
    "recentlyUsedIconsSize": 5,
    "rules": [],
    "extraMargin": {
      "top": 0,
      "right": 4,
      "bottom": 0,
      "left": 0
    },
    "iconInTabsEnabled": true
  },
  "Git Tutorial.md": "SiGit",
  "Commands.md": "FabHashtag",
  "C++.md": "SiCplusplus",
  "Materials": "LiFiles",
  "3-Yocto": "RiUserSettingsLine",
  "3-Yocto/1-Pre-Development.md": "LiCoffee",
  "3-Yocto/2-Development Stage.md": "RiSettings3Line",
  "1-Kernal": "LiSettings",
  "1-Kernal/1-Process Stack & System Calls.md": "FabSquareFontAwesomeStroke",
  "1-Kernal/2-Network Stack.md": "LiNetwork",
  "1-Kernal/3-File System Stack.md": "SiFiles",
  "1-Kernal/4-User Management Stack.md": "LiUsers",
  "1-Kernal/5-Bash Script.md": "SiGnubash",
  "2-Embedded Linux": "SiLinux",
  "2-Embedded Linux/1-Tool Chain.md": "RiToolsFill",
  "2-Embedded Linux/2-Bootloader.md": "SiSpringboot",
  "2-Embedded Linux/3-Kernal.md": "SiLinux",
  "2-Embedded Linux/4-Root File System (Rootfs).md": "LiFiles",
  "2-Embedded Linux/5-System Initialization.md": "IbPlay"
}